deak/__init__.py
deak/converter.py
deak-0.2.0.dist-info/entry_points.txt
deak-0.2.0.dist-info/LICENSE
deak-0.2.0.dist-info/WHEEL
deak-0.2.0.dist-info/METADATA
deak-0.2.0.dist-info/RECORD
