Metadata-Version: 2.1
Name: deak
Version: 0.2.0
Summary: Deak: A Developer's Army Knife.
Author: ryo.ishii
Author-email: ryoishii1101@gmail.com
Requires-Python: >=3.8,<4.0
Classifier: Programming Language :: Python :: 3
Classifier: Programming Language :: Python :: 3.10
Classifier: Programming Language :: Python :: 3.8
Classifier: Programming Language :: Python :: 3.9
Requires-Dist: PyYAML (>=6.0,<7.0)
Requires-Dist: fire (>=0.4.0,<0.5.0)
Requires-Dist: mojimoji (>=0.0.12,<0.0.13)
